cd1/sm.sv
module sm(input reg clk, input logic rst,output reg [2:0] x, 
	output reg[2:0] y);

reg [2:0] vx,vx_d,vy,vy_d;

enum reg [2:0] {
	R,
	incx,
	incy
} cs,ns;

always @(*) begin
	ns=cs;
	vx_d=vx;
	vy_d=vy;
	x=vx;
	y=vy;
	case(cs)
		R: begin
			vx_d=0;
			vy_d=0;
			ns=incx;
		end
		
		incx: begin
			vx_d=vx+1;
			if(vx_d>=4) ns=incy;
		end
		
		incy: begin
			vx_d=0;
			vy_d=vy+1;
			if(vy>=4) begin
				vy_d=0;
				ns=incx;
			end else ns=incx;
		end
		
		default:
			$display("I'm lost with %b",cs);
	endcase

end


always @(posedge(clk) or posedge(rst)) begin
	if(rst) begin
		cs<=R;
		vx<=0;
		vy<=0;
	end else begin
		cs<= #1 ns;
		vx<= #1 vx_d;
		vy<= #1 vy_d;
	end
end


endmodule : sm

cd1/sm1.sv

// A fun system verilog file
`timescale 1ns/10ps

`include "sm.sv"


module top();

logic clk,rst;
reg [2:0] outx,outy;

initial begin
	clk=1;
	repeat(100) begin
		#5 clk=~clk;
	end
end

initial begin
	rst=1;
	repeat(3) @(posedge(clk));
	#1 rst=0;
end

initial begin
	$dumpfile("sm1.vcd");
	$dumpvars(9,top);
	
end

sm bob(clk,rst,outx,outy);

endmodule : top

cd1/sm1.vcd
$date
	Sun Sep  6 23:43:58 2020
$end

$version
	Synopsys VCS version I-2014.03-2
$end

$timescale
	10ps
$end

$comment Csum: 1 af9b9f3c63a30437 $end


$scope module top $end
$var reg 1 ! clk $end
$var reg 1 " rst $end
$var reg 3 # outx [2:0] $end
$var reg 3 $ outy [2:0] $end

$scope module bob $end
$var reg 1 % clk $end
$var reg 1 " rst $end
$var reg 3 # x [2:0] $end
$var reg 3 $ y [2:0] $end
$var reg 3 & vx [2:0] $end
$var reg 3 ' vx_d [2:0] $end
$var reg 3 ( vy [2:0] $end
$var reg 3 ) vy_d [2:0] $end
$var reg 3 * cs [2:0] $end
$var reg 3 + ns [2:0] $end
$upscope $end

$upscope $end

$enddefinitions $end

#0
$dumpvars
1%
1!
1"
b000 *
b001 +
b000 #
b000 $
b000 &
b000 '
b000 (
b000 )
$end
#500
0!
0%
#1000
1!
1%
#1500
0!
0%
#2000
1!
1%
#2500
0!
0%
#3000
1!
1%
#3100
0"
#3500
0!
0%
#4000
1!
1%
#4100
b001 *
b001 '
#4500
0!
0%
#5000
1!
1%
#5100
b001 &
b010 '
b001 #
#5500
0!
0%
#6000
1!
1%
#6100
b010 &
b011 '
b010 #
#6500
0!
0%
#7000
1!
1%
#7100
b011 &
b100 '
b010 +
b011 #
#7500
0!
0%
#8000
1!
1%
#8100
b010 *
b100 &
b001 )
b000 '
b001 +
b100 #
#8500
0!
0%
#9000
1!
1%
#9100
b001 *
b000 &
b001 (
b001 '
b000 #
b001 $
#9500
0!
0%
#10000
1!
1%
#10100
b001 &
b010 '
b001 #
#10500
0!
0%
#11000
1!
1%
#11100
b010 &
b011 '
b010 #
#11500
0!
0%
#12000
1!
1%
#12100
b011 &
b100 '
b010 +
b011 #
#12500
0!
0%
#13000
1!
1%
#13100
b010 *
b100 &
b010 )
b000 '
b001 +
b100 #
#13500
0!
0%
#14000
1!
1%
#14100
b001 *
b000 &
b010 (
b001 '
b000 #
b010 $
#14500
0!
0%
#15000
1!
1%
#15100
b001 &
b010 '
b001 #
#15500
0!
0%
#16000
1!
1%
#16100
b010 &
b011 '
b010 #
#16500
0!
0%
#17000
1!
1%
#17100
b011 &
b100 '
b010 +
b011 #
#17500
0!
0%
#18000
1!
1%
#18100
b010 *
b100 &
b011 )
b000 '
b001 +
b100 #
#18500
0!
0%
#19000
1!
1%
#19100
b001 *
b000 &
b011 (
b001 '
b000 #
b011 $
#19500
0!
0%
#20000
1!
1%
#20100
b001 &
b010 '
b001 #
#20500
0!
0%
#21000
1!
1%
#21100
b010 &
b011 '
b010 #
#21500
0!
0%
#22000
1!
1%
#22100
b011 &
b100 '
b010 +
b011 #
#22500
0!
0%
#23000
1!
1%
#23100
b010 *
b100 &
b100 )
b000 '
b001 +
b100 #
#23500
0!
0%
#24000
1!
1%
#24100
b001 *
b000 &
b100 (
b001 '
b000 #
b100 $
#24500
0!
0%
#25000
1!
1%
#25100
b001 &
b010 '
b001 #
#25500
0!
0%
#26000
1!
1%
#26100
b010 &
b011 '
b010 #
#26500
0!
0%
#27000
1!
1%
#27100
b011 &
b100 '
b010 +
b011 #
#27500
0!
0%
#28000
1!
1%
#28100
b010 *
b100 &
b000 '
b001 +
b000 )
b100 #
#28500
0!
0%
#29000
1!
1%
#29100
b001 *
b000 &
b000 (
b001 '
b000 #
b000 $
#29500
0!
0%
#30000
1!
1%
#30100
b001 &
b010 '
b001 #
#30500
0!
0%
#31000
1!
1%
#31100
b010 &
b011 '
b010 #
#31500
0!
0%
#32000
1!
1%
#32100
b011 &
b100 '
b010 +
b011 #
#32500
0!
0%
#33000
1!
1%
#33100
b010 *
b100 &
b001 )
b000 '
b001 +
b100 #
#33500
0!
0%
#34000
1!
1%
#34100
b001 *
b000 &
b001 (
b001 '
b000 #
b001 $
#34500
0!
0%
#35000
1!
1%
#35100
b001 &
b010 '
b001 #
#35500
0!
0%
#36000
1!
1%
#36100
b010 &
b011 '
b010 #
#36500
0!
0%
#37000
1!
1%
#37100
b011 &
b100 '
b010 +
b011 #
#37500
0!
0%
#38000
1!
1%
#38100
b010 *
b100 &
b010 )
b000 '
b001 +
b100 #
#38500
0!
0%
#39000
1!
1%
#39100
b001 *
b000 &
b010 (
b001 '
b000 #
b010 $
#39500
0!
0%
#40000
1!
1%
#40100
b001 &
b010 '
b001 #
#40500
0!
0%
#41000
1!
1%
#41100
b010 &
b011 '
b010 #
#41500
0!
0%
#42000
1!
1%
#42100
b011 &
b100 '
b010 +
b011 #
#42500
0!
0%
#43000
1!
1%
#43100
b010 *
b100 &
b011 )
b000 '
b001 +
b100 #
#43500
0!
0%
#44000
1!
1%
#44100
b001 *
b000 &
b011 (
b001 '
b000 #
b011 $
#44500
0!
0%
#45000
1!
1%
#45100
b001 &
b010 '
b001 #
#45500
0!
0%
#46000
1!
1%
#46100
b010 &
b011 '
b010 #
#46500
0!
0%
#47000
1!
1%
#47100
b011 &
b100 '
b010 +
b011 #
#47500
0!
0%
#48000
1!
1%
#48100
b010 *
b100 &
b100 )
b000 '
b001 +
b100 #
#48500
0!
0%
#49000
1!
1%
#49100
b001 *
b000 &
b100 (
b001 '
b000 #
b100 $
#49500
0!
0%
#50000
1!
1%
#50100
b001 &
b010 '
b001 #
